yamlmaker/__init__.py
yamlmaker-0.0.8.dist-info/LICENSE
yamlmaker-0.0.8.dist-info/METADATA
yamlmaker-0.0.8.dist-info/WHEEL
yamlmaker-0.0.8.dist-info/top_level.txt
yamlmaker-0.0.8.dist-info/RECORD
