Metadata-Version: 2.1
Name: yamlmaker
Version: 0.0.8
Summary: YAML Generator Utilities
Home-page: https://github.com/anthonyhawkins/yamlmaker
Author: Anthony Hawkins
Author-email: ahawkins.mail@gmail.com
License: UNKNOWN
Project-URL: Bug Tracker, https://github.com/anthonyhawkins/yamlmaker/issues
Platform: UNKNOWN
Classifier: Programming Language :: Python :: 3
Classifier: License :: OSI Approved :: MIT License
Classifier: Operating System :: OS Independent
Requires-Python: >=3.9
License-File: LICENSE
Requires-Dist: pyyaml
